sentra/__init__.py
sentra/client.py
sentra/core/__init__.py
sentra/core/api_error.py
sentra/core/client_wrapper.py
sentra/core/datetime_utils.py
sentra/core/jsonable_encoder.py
sentra/core/remove_none_from_dict.py
sentra/environment.py
sentra/errors/__init__.py
sentra/errors/not_found_error.py
sentra/errors/unprocessable_entity_error.py
sentra/py.typed
sentra/resources/__init__.py
sentra/resources/alerts/__init__.py
sentra/resources/alerts/client.py
sentra/resources/api_keys/__init__.py
sentra/resources/api_keys/client.py
sentra/resources/audit_log/__init__.py
sentra/resources/audit_log/client.py
sentra/resources/connectors/__init__.py
sentra/resources/connectors/client.py
sentra/resources/context_labels/__init__.py
sentra/resources/context_labels/client.py
sentra/resources/dashboard/__init__.py
sentra/resources/dashboard/client.py
sentra/resources/data_access/__init__.py
sentra/resources/data_access/client.py
sentra/resources/data_assets/__init__.py
sentra/resources/data_assets/client.py
sentra/resources/data_classes/__init__.py
sentra/resources/data_classes/client.py
sentra/resources/data_stores/__init__.py
sentra/resources/data_stores/client.py
sentra/resources/export/__init__.py
sentra/resources/export/client.py
sentra/resources/integrations/__init__.py
sentra/resources/integrations/client.py
sentra/resources/policies/__init__.py
sentra/resources/policies/client.py
sentra/resources/roles/__init__.py
sentra/resources/roles/client.py
sentra/resources/sensitivity/__init__.py
sentra/resources/sensitivity/client.py
sentra/resources/users/__init__.py
sentra/resources/users/client.py
sentra/types/__init__.py
sentra/types/access_data_store.py
sentra/types/access_method_accessible_entities_flowchart.py
sentra/types/access_permissions.py
sentra/types/accessible_entities_flowchart_identity_node.py
sentra/types/accessible_entities_flowchart_store_node.py
sentra/types/account_type.py
sentra/types/alert_comment_schema.py
sentra/types/alert_entity_type.py
fern_sentra-0.0.8.dist-info/METADATA
fern_sentra-0.0.8.dist-info/WHEEL
fern_sentra-0.0.8.dist-info/RECORD
